mlp_zygoat_plugins/__init__.py
mlp_zygoat_plugins/images/__init__.py
mlp_zygoat_plugins/images/backend.py
mlp_zygoat_plugins/images/resources/Dockerfile
mlp_zygoat_plugins/images/resources/Dockerfile.local
mlp_zygoat_plugins/images/resources/__init__.py
mlp_zygoat_plugins-0.1.0.dist-info/WHEEL
mlp_zygoat_plugins-0.1.0.dist-info/METADATA
mlp_zygoat_plugins-0.1.0.dist-info/RECORD
